session_retriever/__main__.py
web_session_retriever-0.1.1.dist-info/METADATA
web_session_retriever-0.1.1.dist-info/WHEEL
web_session_retriever-0.1.1.dist-info/entry_points.txt
web_session_retriever-0.1.1.dist-info/top_level.txt
web_session_retriever-0.1.1.dist-info/RECORD
